{
  "schema_version": "0.1",
  "assignment": {
    "slug": "tga-processor",
    "name": "TGA Image Processor",
    "author": "lognd",
    "description": "Implement a command-line TGA image processing tool using structs and binary file I/O."
  },
  "classification": {
    "language": "cpp",
    "difficulty": "hard",
    "topics": [
      "systems",
      "io",
      "memory-management"
    ],
    "course": null
  },
  "template": {
    "slug": "cpp-makefile",
    "version": "0.1"
  },
  "paths": {
    "assignment_root": "assignments/tga-processor",
    "readme": "assignments/tga-processor/README.md",
    "visible_tests": "assignments/tga-processor/visible-tests"
  },
  "state": "draft",
  "source_hash": "sha256:d1af260c119fd9fb8c62037b0dde33aff666eec29e2891b7b4f1a05aae1f9a87"
}
