{
  "schema_version": "0.1",
  "assignment": {
    "slug": "pointer-matrix",
    "name": "Pointer Matrix",
    "author": "lognd",
    "description": "Implement a 2D matrix library using only pointer arithmetic -- the [] operator is forbidden."
  },
  "classification": {
    "language": "cpp",
    "difficulty": "medium",
    "topics": [
      "algorithms",
      "memory-management",
      "data-structures"
    ],
    "course": null
  },
  "template": {
    "slug": "cpp-header-impl",
    "version": "0.1"
  },
  "paths": {
    "assignment_root": "assignments/pointer-matrix",
    "readme": "assignments/pointer-matrix/README.md",
    "visible_tests": "assignments/pointer-matrix/visible-tests"
  },
  "state": "draft",
  "source_hash": "sha256:9e6984deb5d1b73ca4f5ba585ffb0f740aa92ef7646d7f7413abf168ca3a0d44"
}
